heliuspy/__init__.py
heliuspy/api_versions/__init__.py
heliuspy/api_versions/rpc20.py
heliuspy/api_versions/v0.py
heliuspy/utils/__init__.py
heliuspy/utils/curl_helius.py
heliuspy-0.3.0.dist-info/licenses/LICENSE
heliuspy-0.3.0.dist-info/METADATA
heliuspy-0.3.0.dist-info/WHEEL
heliuspy-0.3.0.dist-info/top_level.txt
heliuspy-0.3.0.dist-info/RECORD
