Metadata-Version: 2.4
Name: heliuspy
Version: 0.3.0
Summary: A Python library for Helius endpoints
Author-email: tom <0xtomv@gmail.com>
License: Apache License
Project-URL: Homepage, https://github.com/basedtom/heliuspy
Project-URL: Repository, https://github.com/basedtom/heliuspy.git
Requires-Python: >=3.6
License-File: LICENSE
Requires-Dist: requests
Dynamic: license-file
